source/header.vh
`define OPCODE_WIDTH 6
`define RTYPE 0
`define LOAD 6'h23
`define LOAD_BYTE_UNSIGNED 6'h24
`define LOAD_HALF_UNSIGNED 6'h25
`define LOAD_BYTE 6'h26
`define LOAD_HALF 6'h27
`define STORE 6'h2b
`define STORE_BYTE 6'h2c
`define STORE_HALF 6'h2d
`define BEQ 6'h4
`define BNE 6'h5
`define ADDI 6'h8
`define ADDIU 6'h9
`define SLTI 6'ha
`define SLTIU 6'hb
`define ANDI 6'hc
`define ORI 6'hd
`define LUI 6'hf
`define JAL 6'h3

`define FUNCT_WIDTH 6
`define ADD 6'b100000
`define SUB 6'b100010
`define SUBU 6'b100011
`define AND 6'b100100
`define OR 6'b100101
`define NOR 6'b100111
`define SLT 6'b101010
`define SLTU 6'b101011
`define SLL 6'b000000
`define SRL 6'b000010
`define SRA 6'b101001
`define EQ 6'b001100
`define NEQ 6'b001101
`define GE 6'b101100
`define GEU 6'b101101
`define ADDU 6'b100001
`define JR 6'b001000

`define DWIDTH 32
`define IWIDTH 32
`define AWIDTH 5
`define PC_WIDTH 32
`define AWIDTH_MEM 32
`define IMM_WIDTH 16
`define ALU_CONTROL 5
`define JUMP_WIDTH 26
`define DEPTH 2

source/memory.v
`ifndef MEMORY_V
`define MEMORY_V
`include "./source/header.vh"
module memory (
    m_clk, m_rst, m_wr_en, m_i_ce, m_i_store_data, 
    alu_value_addr, m_o_load_data, m_i_mask
);
    input m_clk, m_rst;
    input m_wr_en;  
    input m_i_ce;
    input [`AWIDTH_MEM - 1 : 0] alu_value_addr;
    input [`DWIDTH - 1 : 0] m_i_store_data;
    input [3 : 0] m_i_mask;
    output [`DWIDTH - 1 : 0] m_o_load_data;
    integer i;
    reg [`DWIDTH - 1 : 0] data_mem [0 : `AWIDTH_MEM - 1];

    always @(negedge m_clk, negedge m_rst) begin
        if (!m_rst) begin
            for (i = 0; i < `AWIDTH_MEM; i = i + 1) begin
                data_mem[i] <= i;   
            end
        end
        else begin
            if (m_i_ce) begin
                if (m_wr_en) begin
                    if (m_i_mask[0]) begin
                        data_mem[alu_value_addr][7 : 0] <= m_i_store_data[7 : 0];
                    end
                    if (m_i_mask[1]) begin
                        data_mem[alu_value_addr][15 : 8] <= m_i_store_data[15 : 8];
                    end
                    if (m_i_mask[2]) begin
                        data_mem[alu_value_addr][23 : 16] <= m_i_store_data[23 : 16];
                    end
                    if (m_i_mask[3]) begin
                        data_mem[alu_value_addr][31 : 24] <= m_i_store_data[31 : 24];
                    end
                end
            end
        end
    end
    assign m_o_load_data = data_mem[alu_value_addr];
endmodule
`endif

test/tb_memory.v
`timescale 1ns/1ps
`include "./source/memory.v"

module tb;
    reg m_clk, m_rst;
    reg m_wr_en;
    reg m_i_ce;
    reg [`AWIDTH_MEM - 1 : 0] alu_value_addr;
    reg [`DWIDTH - 1 : 0] m_i_store_data;
    reg [3 : 0] m_i_mask;
    wire [`DWIDTH - 1 : 0] m_o_load_data;
    integer i;

    memory m (
        .m_clk(m_clk), 
        .m_rst(m_rst), 
        .m_wr_en(m_wr_en), 
        .m_i_ce(m_i_ce), 
        .alu_value_addr(alu_value_addr),
        .m_i_store_data(m_i_store_data),
        .m_i_mask(m_i_mask),  
        .m_o_load_data(m_o_load_data)
    );

    // Clock 10ns
    initial begin
        m_clk = 1'b0;
        forever #5 m_clk = ~m_clk;
    end

    // Dump waveform
    initial begin
        $dumpfile("./waveform/memory.vcd");
        $dumpvars(0, tb);
    end

    // Reset task
    task reset (input integer cycles);
        begin
            m_rst = 1'b0;
            repeat(cycles) @(posedge m_clk);
            m_rst = 1'b1;
            @(posedge m_clk);
        end
    endtask

    // Task ghi dữ liệu với mask
    task store_data(input [3:0] mask, input [31:0] data, input [31:0] addr);
        begin
            @(posedge m_clk);
            m_i_ce = 1'b1;
            m_wr_en = 1'b1;
            m_i_mask = mask;
            alu_value_addr = addr;
            m_i_store_data = data;
            @(posedge m_clk);
            m_wr_en = 1'b0;
        end
    endtask

    // Task đọc dữ liệu
    task load_data(input [31:0] addr);
        begin
            @(posedge m_clk);
            m_i_ce = 1'b1;
            alu_value_addr = addr;
            @(posedge m_clk);
            $display("[%0t] Addr=%0d => Load Data=0x%08h", $time, alu_value_addr, m_o_load_data);
        end
    endtask

    initial begin
        // Reset memory
        reset(2);

        // --- TEST 1: STORE WORD (ghi đủ 4 byte) ---
        $display("\n==== TEST 1: STORE WORD ====");
        store_data(4'b1111, 32'hAABBCCDD, 3);
        load_data(3);

        // --- TEST 2: STORE HALF (ghi 2 byte thấp) ---
        $display("\n==== TEST 2: STORE HALF ====");
        store_data(4'b0011, 32'h0000EEFF, 4);
        load_data(4);

        // --- TEST 3: STORE BYTE (ghi 1 byte thấp) ---
        $display("\n==== TEST 3: STORE BYTE ====");
        store_data(4'b0001, 32'h00000099, 5);
        load_data(5);

        // --- TEST 4: GHI NHIỀU GIÁ TRỊ ---
        $display("\n==== TEST 4: MULTI WRITE LOOP ====");
        for (i = 0; i < 8; i = i + 1) begin
            store_data(4'b1111, i * 16 + 8, i);
        end
        for (i = 0; i < 8; i = i + 1) begin
            load_data(i);
        end

        $display("\nSimulation Done.\n");
        #50 $finish;
    end
endmodule

waveform/memory.vcd
$date
	Sat Oct 18 14:59:44 2025
$end
$version
	Icarus Verilog
$end
$timescale
	1ps
$end
$scope module tb $end
$var wire 32 ! m_o_load_data [31:0] $end
$var reg 32 " alu_value_addr [31:0] $end
$var integer 32 # i [31:0] $end
$var reg 1 $ m_clk $end
$var reg 1 % m_i_ce $end
$var reg 4 & m_i_mask [3:0] $end
$var reg 32 ' m_i_store_data [31:0] $end
$var reg 1 ( m_rst $end
$var reg 1 ) m_wr_en $end
$scope module m $end
$var wire 32 * alu_value_addr [31:0] $end
$var wire 1 + m_clk $end
$var wire 1 , m_i_ce $end
$var wire 4 - m_i_mask [3:0] $end
$var wire 32 . m_i_store_data [31:0] $end
$var wire 32 / m_o_load_data [31:0] $end
$var wire 1 0 m_rst $end
$var wire 1 1 m_wr_en $end
$var integer 32 2 i [31:0] $end
$upscope $end
$scope task load_data $end
$var reg 32 3 addr [31:0] $end
$upscope $end
$scope task reset $end
$var integer 32 4 cycles [31:0] $end
$upscope $end
$scope task store_data $end
$var reg 32 5 addr [31:0] $end
$var reg 32 6 data [31:0] $end
$var reg 4 7 mask [3:0] $end
$upscope $end
$upscope $end
$enddefinitions $end
#0
$dumpvars
bx 7
bx 6
bx 5
b10 4
bx 3
b100000 2
x1
00
bx /
bx .
bx -
x,
0+
bx *
x)
0(
bx '
bx &
x%
0$
bx #
bx "
bx !
$end
#5000
1$
1+
#10000
b100000 2
0$
0+
#15000
1(
10
1$
1+
#20000
0$
0+
#25000
b11 5
b10101010101110111100110011011101 6
b1111 7
1$
1+
#30000
0$
0+
#35000
b10101010101110111100110011011101 '
b10101010101110111100110011011101 .
b11 "
b11 *
b11 !
b11 /
b1111 &
b1111 -
1)
11
1%
1,
1$
1+
#40000
b10101010101110111100110011011101 !
b10101010101110111100110011011101 /
0$
0+
#45000
b11 3
0)
01
1$
1+
#50000
0$
0+
#55000
1$
1+
#60000
0$
0+
#65000
b100 5
b1110111011111111 6
b11 7
1$
1+
#70000
0$
0+
#75000
b1110111011111111 '
b1110111011111111 .
b100 "
b100 *
b100 !
b100 /
b11 &
b11 -
1)
11
1$
1+
#80000
b1110111011111111 !
b1110111011111111 /
0$
0+
#85000
b100 3
0)
01
1$
1+
#90000
0$
0+
#95000
1$
1+
#100000
0$
0+
#105000
b101 5
b10011001 6
b1 7
1$
1+
#110000
0$
0+
#115000
b10011001 '
b10011001 .
b101 "
b101 *
b101 !
b101 /
b1 &
b1 -
1)
11
1$
1+
#120000
b10011001 !
b10011001 /
0$
0+
#125000
b101 3
0)
01
1$
1+
#130000
0$
0+
#135000
1$
1+
#140000
0$
0+
#145000
b0 5
b1000 6
b1111 7
b0 #
1$
1+
#150000
0$
0+
#155000
b1000 '
b1000 .
b0 "
b0 *
b0 !
b0 /
b1111 &
b1111 -
1)
11
1$
1+
#160000
b1000 !
b1000 /
0$
0+
#165000
b1 5
b11000 6
b1 #
0)
01
1$
1+
#170000
0$
0+
#175000
b11000 '
b11000 .
b1 "
b1 *
b1 !
b1 /
1)
11
1$
1+
#180000
b11000 !
b11000 /
0$
0+
#185000
b10 5
b101000 6
b10 #
0)
01
1$
1+
#190000
0$
0+
#195000
b101000 '
b101000 .
b10 "
b10 *
b10 !
b10 /
1)
11
1$
1+
#200000
b101000 !
b101000 /
0$
0+
#205000
b11 5
b111000 6
b11 #
0)
01
1$
1+
#210000
0$
0+
#215000
b111000 '
b111000 .
b11 "
b11 *
b10101010101110111100110011011101 !
b10101010101110111100110011011101 /
1)
11
1$
1+
#220000
b111000 !
b111000 /
0$
0+
#225000
b100 5
b1001000 6
b100 #
0)
01
1$
1+
#230000
0$
0+
#235000
b1001000 '
b1001000 .
b100 "
b100 *
b1110111011111111 !
b1110111011111111 /
1)
11
1$
1+
#240000
b1001000 !
b1001000 /
0$
0+
#245000
b101 5
b1011000 6
b101 #
0)
01
1$
1+
#250000
0$
0+
#255000
b1011000 '
b1011000 .
b101 "
b101 *
b10011001 !
b10011001 /
1)
11
1$
1+
#260000
b1011000 !
b1011000 /
0$
0+
#265000
b110 5
b1101000 6
b110 #
0)
01
1$
1+
#270000
0$
0+
#275000
b1101000 '
b1101000 .
b110 "
b110 *
b110 !
b110 /
1)
11
1$
1+
#280000
b1101000 !
b1101000 /
0$
0+
#285000
b111 5
b1111000 6
b111 #
0)
01
1$
1+
#290000
0$
0+
#295000
b1111000 '
b1111000 .
b111 "
b111 *
b111 !
b111 /
1)
11
1$
1+
#300000
b1111000 !
b1111000 /
0$
0+
#305000
b0 3
b0 #
0)
01
1$
1+
#310000
0$
0+
#315000
b0 "
b0 *
b1000 !
b1000 /
1$
1+
#320000
0$
0+
#325000
b1 3
b1 #
1$
1+
#330000
0$
0+
#335000
b1 "
b1 *
b11000 !
b11000 /
1$
1+
#340000
0$
0+
#345000
b10 3
b10 #
1$
1+
#350000
0$
0+
#355000
b10 "
b10 *
b101000 !
b101000 /
1$
1+
#360000
0$
0+
#365000
b11 3
b11 #
1$
1+
#370000
0$
0+
#375000
b11 "
b11 *
b111000 !
b111000 /
1$
1+
#380000
0$
0+
#385000
b100 3
b100 #
1$
1+
#390000
0$
0+
#395000
b100 "
b100 *
b1001000 !
b1001000 /
1$
1+
#400000
0$
0+
#405000
b101 3
b101 #
1$
1+
#410000
0$
0+
#415000
b101 "
b101 *
b1011000 !
b1011000 /
1$
1+
#420000
0$
0+
#425000
b110 3
b110 #
1$
1+
#430000
0$
0+
#435000
b110 "
b110 *
b1101000 !
b1101000 /
1$
1+
#440000
0$
0+
#445000
b111 3
b111 #
1$
1+
#450000
0$
0+
#455000
b111 "
b111 *
b1111000 !
b1111000 /
1$
1+
#460000
0$
0+
#465000
b1000 #
1$
1+
