source/header.vh
`define OPCODE_WIDTH 6
`define RTYPE 6'h0
`define BEQ 6'h4
`define BNE 6'h5
`define ORI 6'hd
`define LUI 6'hf
`define JAL 6'h3
`define SLTI 6'ha
`define ADDI 6'h8
`define ANDI 6'hc
`define ADDIU 6'h9
`define SLTIU 6'hb
`define STORE_WORD 6'h2b
`define STORE_BYTE 6'h2c
`define STORE_HALF 6'h2d
`define LOAD_WORD 6'h23
`define LOAD_BYTE 6'h26
`define LOAD_HALF 6'h27
`define LOAD_BYTE_UNSIGNED 6'h24
`define LOAD_HALF_UNSIGNED 6'h25

`define FUNCT_WIDTH 6
`define ADD 6'b100000
`define SUB 6'b100010
`define SUBU 6'b100011
`define AND 6'b100100
`define OR 6'b100101
`define NOR 6'b100111
`define SLT 6'b101010
`define SLTU 6'b101011
`define SLL 6'b000000
`define SRL 6'b000010
`define SRA 6'b101001
`define EQ 6'b001100
`define NEQ 6'b001101
`define GE 6'b101100
`define GEU 6'b101101
`define ADDU 6'b100001
`define JR 6'b001000

`define DWIDTH 32
`define IWIDTH 32
`define AWIDTH 5
`define PC_WIDTH 32
`define AWIDTH_MEM 32
`define IMM_WIDTH 16
`define ALU_CONTROL 5
`define JUMP_WIDTH 26
`define DEPTH 2

source/program_counter.v
`ifndef PROGRAM_COUNTER_V
`define PROGRAM_COUNTER_V
`include "./source/header.vh"
module prog_counter (
    pc_clk, pc_rst, pc_i_ce, pc_i_change_pc, pc_i_pc, pc_o_pc, pc_o_ce
);
    input pc_i_ce;
    input pc_clk, pc_rst;
    input pc_i_change_pc;
    input [`PC_WIDTH - 1 : 0] pc_i_pc;
    output reg pc_o_ce;
    output reg [`PC_WIDTH - 1 : 0] pc_o_pc;
    reg [`PC_WIDTH - 1 : 0] temp_pc;

    always @(posedge pc_clk or negedge pc_rst) begin
        if (!pc_rst) begin
            pc_o_ce <= 1'b0;
            pc_o_pc <= {`PC_WIDTH{1'b0}};
            temp_pc <= {`PC_WIDTH{1'b0}};
        end
        else begin
            if (pc_i_ce) begin
                pc_o_ce <= 1'b1;
                pc_o_pc <= temp_pc;
                if (pc_i_change_pc) begin
                    temp_pc <= pc_i_pc;
                end
                else begin
                    temp_pc <= temp_pc + 4;
                end
            end
        end
    end
endmodule
`endif

test/tb_pc.v
`include "./source/program_counter.v"

module tb;
    reg pc_clk, pc_rst;
    reg pc_i_ce;
    reg pc_i_change_pc;
    reg [`PC_WIDTH - 1 : 0] pc_i_pc;
    wire [`PC_WIDTH - 1 : 0] pc_o_pc;
    wire pc_o_ce;

    prog_counter pc (
        .pc_clk(pc_clk), 
        .pc_rst(pc_rst), 
        .pc_i_ce(pc_i_ce), 
        .pc_i_change_pc(pc_i_change_pc), 
        .pc_i_pc(pc_i_pc), 
        .pc_o_pc(pc_o_pc), 
        .pc_o_ce(pc_o_ce)
    );

    initial begin
        pc_clk = 1'b0;
    end
    always #5 pc_clk = ~pc_clk;

    initial begin
        $dumpfile("./waveform/pc.vcd");
        $dumpvars(0, tb);
    end

    task reset (input integer counter);
        begin 
            pc_rst = 1'b0;
            repeat(counter) @(posedge pc_clk);
            pc_rst = 1'b1;
        end
    endtask

    initial begin
        reset(2);
        @(posedge pc_clk);
        pc_i_ce = 1'b1;
        repeat(20) @(posedge pc_clk);
        // pc_i_change_pc = 1'b1;
        // pc_i_pc = 10;
        // @(posedge pc_clk);
        // pc_i_change_pc = 1'b0;
        #20; $finish;
    end

    initial begin
        $monitor($time, " ", "pc_o_ce = %b, pc_o_pc = %d", pc_o_ce, pc_o_pc);
    end
endmodule

waveform/pc.vcd
$date
	Sat Nov 01 13:37:05 2025
$end
$version
	Icarus Verilog
$end
$timescale
	1s
$end
$scope module tb $end
$var wire 1 ! pc_o_ce $end
$var wire 32 " pc_o_pc [31:0] $end
$var reg 1 # pc_clk $end
$var reg 1 $ pc_i_ce $end
$var reg 1 % pc_i_change_pc $end
$var reg 32 & pc_i_pc [31:0] $end
$var reg 1 ' pc_rst $end
$scope module pc $end
$var wire 1 ( pc_clk $end
$var wire 1 ) pc_i_ce $end
$var wire 1 * pc_i_change_pc $end
$var wire 32 + pc_i_pc [31:0] $end
$var wire 1 , pc_rst $end
$var reg 1 - pc_o_ce $end
$var reg 32 . pc_o_pc [31:0] $end
$var reg 32 / temp_pc [31:0] $end
$upscope $end
$scope task reset $end
$var integer 32 0 counter [31:0] $end
$upscope $end
$upscope $end
$enddefinitions $end
#0
$dumpvars
b10 0
b0 /
b0 .
0-
0,
bx +
x*
x)
0(
0'
bx &
x%
x$
0#
b0 "
0!
$end
#5
1#
1(
#10
0#
0(
#15
1'
1,
1#
1(
#20
0#
0(
#25
b100 /
1-
1!
1$
1)
1#
1(
#30
0#
0(
#35
b1000 /
b100 .
b100 "
1#
1(
#40
0#
0(
#45
b1100 /
b1000 .
b1000 "
1#
1(
#50
0#
0(
#55
b10000 /
b1100 .
b1100 "
1#
1(
#60
0#
0(
#65
b10100 /
b10000 .
b10000 "
1#
1(
#70
0#
0(
#75
b11000 /
b10100 .
b10100 "
1#
1(
#80
0#
0(
#85
b11100 /
b11000 .
b11000 "
1#
1(
#90
0#
0(
#95
b100000 /
b11100 .
b11100 "
1#
1(
#100
0#
0(
#105
b100100 /
b100000 .
b100000 "
1#
1(
#110
0#
0(
#115
b101000 /
b100100 .
b100100 "
1#
1(
#120
0#
0(
#125
b101100 /
b101000 .
b101000 "
1#
1(
#130
0#
0(
#135
b110000 /
b101100 .
b101100 "
1#
1(
#140
0#
0(
#145
b110100 /
b110000 .
b110000 "
1#
1(
#150
0#
0(
#155
b111000 /
b110100 .
b110100 "
1#
1(
#160
0#
0(
#165
b111100 /
b111000 .
b111000 "
1#
1(
#170
0#
0(
#175
b1000000 /
b111100 .
b111100 "
1#
1(
#180
0#
0(
#185
b1000100 /
b1000000 .
b1000000 "
1#
1(
#190
0#
0(
#195
b1001000 /
b1000100 .
b1000100 "
1#
1(
#200
0#
0(
#205
b1001100 /
b1001000 .
b1001000 "
1#
1(
#210
0#
0(
#215
b1010000 /
b1001100 .
b1001100 "
1#
1(
#220
0#
0(
#225
b1010100 /
b1010000 .
b1010000 "
1#
1(
#230
0#
0(
#235
b1011000 /
b1010100 .
b1010100 "
1#
1(
#240
0#
0(
#245
b1011100 /
b1011000 .
b1011000 "
1#
1(
